musescore_scraper/MuseScraper.py
musescore_scraper/__init__.py
musescore_scraper/helper.py
musescore_scraper/script.js
musescore_scraper-2.4.0.dist-info/LICENSE
musescore_scraper-2.4.0.dist-info/METADATA
musescore_scraper-2.4.0.dist-info/WHEEL
musescore_scraper-2.4.0.dist-info/entry_points.txt
musescore_scraper-2.4.0.dist-info/top_level.txt
musescore_scraper-2.4.0.dist-info/RECORD
