Metadata-Version: 2.1
Name: musescore-scraper
Version: 2.4.0
Summary: A MuseScore PDF scraper.
Home-page: https://github.com/jasyip/musescore-scraper
Author: Jason Yip
Author-email: jasonyip1234567@gmail.com
License: MIT
Keywords: musescore,pdf,scraper
Platform: UNKNOWN
Classifier: Programming Language :: Python :: 3.8
Requires-Python: >=3.8
License-File: LICENSE
Requires-Dist: PyPDF2
Requires-Dist: pyppeteer
Requires-Dist: reportlab
Requires-Dist: requests
Requires-Dist: svglib
Provides-Extra: docs
Requires-Dist: sphinx ; extra == 'docs'
Requires-Dist: myst-parser ; extra == 'docs'
Provides-Extra: test
Requires-Dist: pytest ; extra == 'test'
Requires-Dist: pytest-asyncio ; extra == 'test'
